magnum_ui/__init__.py
magnum_ui/karma.conf.js
magnum_ui/version.py
magnum_ui/api/__init__.py
magnum_ui/api/heat.py
magnum_ui/api/magnum.py
magnum_ui/api/rest/__init__.py
magnum_ui/api/rest/magnum.py
magnum_ui/content/__init__.py
magnum_ui/content/cluster_templates/__init__.py
magnum_ui/content/cluster_templates/panel.py
magnum_ui/content/cluster_templates/tests.py
magnum_ui/content/cluster_templates/urls.py
magnum_ui/content/clusters/__init__.py
magnum_ui/content/clusters/panel.py
magnum_ui/content/clusters/tests.py
magnum_ui/content/clusters/urls.py
magnum_ui/content/container_infra/__init__.py
magnum_ui/content/container_infra/quotas/__init__.py
magnum_ui/content/container_infra/quotas/panel.py
magnum_ui/content/container_infra/quotas/urls.py
magnum_ui/enabled/_1370_project_container_infra_panel_group.py
magnum_ui/enabled/_1371_project_container_infra_clusters_panel.py
magnum_ui/enabled/_1372_project_container_infra_cluster_templates_panel.py
magnum_ui/enabled/_2370_admin_container_infra_panel_group.py
magnum_ui/enabled/_2371_admin_container_infra_quotas_panel.py
magnum_ui/enabled/__init__.py
magnum_ui/locale/cs/LC_MESSAGES/django.po
magnum_ui/locale/de/LC_MESSAGES/django.po
magnum_ui/locale/de/LC_MESSAGES/djangojs.po
magnum_ui/locale/en_AU/LC_MESSAGES/djangojs.po
magnum_ui/locale/en_GB/LC_MESSAGES/django.po
magnum_ui/locale/en_GB/LC_MESSAGES/djangojs.po
magnum_ui/locale/fr/LC_MESSAGES/django.po
magnum_ui/locale/fr/LC_MESSAGES/djangojs.po
magnum_ui/locale/id/LC_MESSAGES/django.po
magnum_ui/locale/id/LC_MESSAGES/djangojs.po
magnum_ui/locale/ja/LC_MESSAGES/django.po
magnum_ui/locale/ja/LC_MESSAGES/djangojs.po
magnum_ui/locale/ko_KR/LC_MESSAGES/django.po
magnum_ui/locale/ko_KR/LC_MESSAGES/djangojs.po
magnum_ui/locale/pt_BR/LC_MESSAGES/django.po
magnum_ui/locale/pt_BR/LC_MESSAGES/djangojs.po
magnum_ui/locale/ru/LC_MESSAGES/django.po
magnum_ui/locale/ru/LC_MESSAGES/djangojs.po
magnum_ui/locale/tr_TR/LC_MESSAGES/django.po
magnum_ui/locale/tr_TR/LC_MESSAGES/djangojs.po
magnum_ui-17.0.0.dist-info/AUTHORS
magnum_ui-17.0.0.dist-info/LICENSE
magnum_ui-17.0.0.dist-info/METADATA
magnum_ui-17.0.0.dist-info/WHEEL
magnum_ui-17.0.0.dist-info/pbr.json
magnum_ui-17.0.0.dist-info/top_level.txt
magnum_ui-17.0.0.dist-info/RECORD
