Metadata-Version: 2.1
Name: magnum-ui
Version: 17.0.0
Summary: Magnum User Interface
Home-page: https://docs.openstack.org/developer/magnum-ui/
Author: OpenStack
Author-email: openstack-discuss@lists.openstack.org
Classifier: Environment :: OpenStack
Classifier: Intended Audience :: Information Technology
Classifier: Intended Audience :: System Administrators
Classifier: License :: OSI Approved :: Apache Software License
Classifier: Operating System :: POSIX :: Linux
Classifier: Programming Language :: Python
Classifier: Programming Language :: Python :: 3
Classifier: Programming Language :: Python :: 3.6
Classifier: Programming Language :: Python :: 3.7
Classifier: Programming Language :: Python :: 3.8
Classifier: Programming Language :: Python :: 3.9
Classifier: Programming Language :: Python :: 3.10
Classifier: Programming Language :: Python :: 3.11
License-File: LICENSE
License-File: AUTHORS
Requires-Dist: pbr !=2.1.0,>=2.0.0
Requires-Dist: python-magnumclient >=4.9.0
Requires-Dist: python-heatclient >=1.18.0
Requires-Dist: horizon >=17.1.0
